{
  "id": "OL1308096W",
  "title": "Suite française",
  "description": "Écrit dans le feu de l'Histoire, Suite française dépeint presque en direct l'Exode de juin 1940, qui brassa dans un désordre tragique des familles françaises de toute sorte, des plus huppées aux plus modestes. Avec bonheur, Irène Némirovsky traque les innombrables petites lâchetés et les fragiles élans de solidarité d'une population en déroute. Cocottes larguées par leur amant, grands bourgeois dégoûtés par la populace, blessés abandonnés dans des fermes engorgent les routes de France bombardées au hasard... Peu à peu l'ennemi prend possession d'un pays inerte et apeuré. Comme tant d'autres, le village de Bussy est alors contraint d'accueillir des troupes allemandes. Exacerbées par la présence de l'occupant, les tensions sociales et frustrations des habitants se réveillent...Roman bouleversant, intimiste, implacable, dévoilant avec une extraordinaire lucidité l'âme de chaque Français pendant l'Occupation (enrichi de notes et de la correspondance d'Irène Némirovsky), Suite française ressuscite d'une plume brillante et intuitive un pan à vif de notre mémoire.",
  "authors": [
    "Irène Némirovsky"
  ],
  "first_publish_year": 2004,
  "subjects": [
    "Correspondence",
    "Fiction",
    "World War, 1939-1945",
    "History",
    "Historical fiction",
    "German occupation",
    "Literature",
    "Historical - General",
    "Fiction - Historical",
    "German Occupation of France (1940-1945) fast (OCoLC)fst01353176",
    "Large type books",
    "French fiction",
    "Translations into Vietnamese",
    "Guerre, 1939-1945 (Mondiale, 2e)",
    "Romans, nouvelles",
    "Histoire",
    "France, fiction",
    "Fiction, historical",
    "World war, 1939-1945, fiction",
    "Fiction, historical, general",
    "Fiction, war & military",
    "World war, 1939-1945--france--fiction",
    "Pq2627.e4 s8513 2006",
    "000119625",
    "843/.912",
    "World literature",
    "Fiction subjects",
    "Peoples & cultures - fiction",
    "Dünya Savaşı, 1939-1945",
    "Roman",
    "Tarih"
  ],
  "language": [
    "heb",
    "spa",
    "rus",
    "ger",
    "baq",
    "fre",
    "vie",
    "eng",
    "ita"
  ],
  "openlibrary_url": "https://openlibrary.org/works/OL1308096W"
}