{
  "id": "OL14871282W",
  "title": "Captain Underpants and the Perilous Plot of Professor Poopypants",
  "description": "Por burlarse del nombre del profesor Pipicaca, Jorge y Beto están a punto de hacer que su nuevo maestro de ciencia enloquecido de rabia se apodere del planeta entero. Pero Capitán Calzoncillos viene al rescate.\r\n\r\nWhen Professor Pippy P. Poopypants comes to Jerome Horwitz Elementary School to teach science, and he goes off the deep end because students make fun of his name, only Captain Underpants can save the school from the professor's perilous plot.",
  "authors": [
    "Dav Pilkey"
  ],
  "first_publish_year": 2000,
  "subjects": [
    "Humorous stories",
    "Héroes",
    "Juvenile fiction",
    "School principals",
    "Ficción juvenil",
    "Cartoons and comics",
    "Superintendentes y directores",
    "Escuelas",
    "Cuentos humorísticos",
    "Schools",
    "Heroes",
    "Fiction",
    "Children's fiction",
    "Schools, fiction",
    "Heroes, fiction",
    "Captain underpants (fictitious character), fiction",
    "Teachers, fiction",
    "Adventure and adventurers, fiction",
    "Bilingual books, spanish-english",
    "Captain",
    "Underpants",
    "Children's",
    "Captain Underpants (Fictitious character)",
    "Science fiction",
    "Bandes dessinées",
    "Romans pour la jeunesse",
    "Héros",
    "Récits humoristiques",
    "Caricatures and cartoons",
    "Directeurs d'école",
    "Écoles",
    "Robots, fiction"
  ],
  "language": [
    "eng",
    "spa",
    "cat",
    "fre",
    "tur",
    "chi",
    "heb"
  ],
  "openlibrary_url": "https://openlibrary.org/works/OL14871282W"
}