{
  "id": "OL149119W",
  "title": "Duma Key",
  "description": "Duma Key is a novel by American writer Stephen King published on January 22, 2008 by Scribner. The book reached No. 1 on the New York Times Best Seller List. It is King's first novel to be set in Florida and/or Minnesota.",
  "authors": [
    "Stephen King"
  ],
  "first_publish_year": 2008,
  "subjects": [
    "Accidentes",
    "Accident victims",
    "Paranormal fiction",
    "Sobrenatural",
    "Novela",
    "Ficción",
    "Fiction",
    "Supernatural in fiction",
    "Supernatural",
    "Accident victims in fiction",
    "Painters",
    "Missing persons",
    "Investigation",
    "Fiction, horror",
    "Florida, fiction",
    "Artists, fiction",
    "Missing persons, fiction",
    "Fiction, mystery & detective, general",
    "Accidents",
    "Romans, nouvelles",
    "Surnaturel",
    "nyt:mass-market-paperback=2008-11-09",
    "New York Times bestseller",
    "New York Times reviewed",
    "Social sciences",
    "Bibliography",
    "Fiction, occult & supernatural",
    "Accident victims -- Fiction",
    "Supernatural -- Fiction",
    "Florida Keys (Fla.) -- Fiction"
  ],
  "language": [
    "chi",
    "por",
    "dut",
    "spa",
    "pol",
    "ger",
    "fre",
    "eng"
  ],
  "openlibrary_url": "https://openlibrary.org/works/OL149119W"
}