{
  "id": "OL15192743W",
  "title": "The Ugly Truth",
  "description": "###German-language description:\r\nGreg hat´s offenbar eilig, schnell älter zu werden. Aber ist das wirklich so eine gute Idee?Jedenfalls muss er feststellen: Erwachsenwerden ist gar nicht lustig! Denn plötzlich soll Greg \"mehr Verantwortung\" übernehmen, mehr duschen und Deo benutzen, in der Schule peinliche Aufklärungsvideos ansehen und Bücher über die Pubertät lesen. Und dann verkündet seine Mutter auch noch, dass sie wieder studieren will. Soll Greg sich jetzt etwa seine Pausenbrote selbst schmieren, die Wäsche waschen und den Haushalt schmeißen?",
  "authors": [
    "Jeff Kinney"
  ],
  "first_publish_year": 2001,
  "subjects": [
    "nyt:series_books=2009-01-10",
    "New York Times bestseller",
    "Maturation (Psychology)",
    "Humorous stories",
    "Families",
    "Diaries",
    "Juvenile fiction",
    "Family life",
    "Fiction",
    "Friendship",
    "Children's fiction",
    "Family life, fiction",
    "Diaries, fiction",
    "Friendship, fiction",
    "Bullying",
    "Child and youth fiction",
    "Cartoons and comics",
    "Humorous fiction",
    "Comics & Graphic Novels",
    "Accelerated Reader",
    "Summer",
    "Vacations",
    "Video games",
    "Été",
    "Romans, nouvelles, etc. pour la jeunesse",
    "Journaux intimes",
    "Jeux vidéo",
    "Cuentos infantiles estadounidenses",
    "Escuelas secundarias",
    "Novela",
    "Amistad",
    "Fiestas",
    "Escuelas",
    "Familia",
    "Adolescentes",
    "Novela norteamericana",
    "Novela costumbrista",
    "Familles",
    "Amitié",
    "Intimidation",
    "Comic-Roman",
    "Familie",
    "Humor",
    "Chaos",
    "Erwachsenwerden",
    "Verantwortung tragen",
    "Pubertät",
    "Selbstständigkeit"
  ],
  "language": [
    "kor",
    "wel",
    "pol",
    "dut",
    "spa",
    "jpn",
    "bul",
    "cat",
    "chi",
    "eng",
    "ger",
    "fre"
  ],
  "openlibrary_url": "https://openlibrary.org/works/OL15192743W"
}