{
  "id": "OL15008W",
  "title": "The Collector",
  "description": "Fowles’ stunning debut is a study of a lonely young sociopath who kidnaps the woman he has fixated on, keeping her in his cellar in the belief that she will eventually come to love him. The story is narrated in turns by the young man and his captive, giving two opposing points of view.",
  "authors": [
    "John Fowles"
  ],
  "first_publish_year": 1963,
  "subjects": [
    "English Horror tales",
    "Butterflies",
    "Collection and preservation",
    "Fiction",
    "Kidnapping",
    "Psychopaths",
    "Translations into Russian",
    "England",
    "Mentally ill",
    "Crimes against",
    "Young women",
    "Collectors and collecting",
    "British and irish fiction (fictional works by one author)",
    "Fiction, psychological",
    "Art"
  ],
  "language": [
    "ger",
    "ukr",
    "eng",
    "chi",
    "spa",
    "rus"
  ],
  "openlibrary_url": "https://openlibrary.org/works/OL15008W"
}