{
  "id": "OL16894032W",
  "title": "Good wives",
  "description": "Three years from Little Women, this is the second story about the March sisters, Meg, Jo, Beth, and Amy and their friend Laurie as each grows from childhood into adulthood. Life promises adventures, fulfillment and painful trials along the way, marriage, disappointment in love and a tragedy which touches them all, each of them finally finds happiness, if not always in the way they expect.",
  "authors": [
    "Louisa May Alcott"
  ],
  "first_publish_year": 1870,
  "subjects": [
    "Soeurs",
    "Femmes mariées",
    "Fiction",
    "Romans",
    "Sisters",
    "Married women",
    "Jeunes filles",
    "Young women",
    "Girls, fiction",
    "Children's fiction",
    "Women, fiction",
    "Sisters, fiction",
    "Married people",
    "Women, biography",
    "Wives",
    "History",
    "Women",
    "American literature"
  ],
  "language": [
    "eng",
    "chi"
  ],
  "openlibrary_url": "https://openlibrary.org/works/OL16894032W"
}