{
  "id": "OL167331W",
  "title": "The Alibi",
  "description": "An honorable man. . . a very sexy dilemma.\r\n\r\nHammond Cross is a man caught in a moral dilemma.\r\n\r\nThe plot of THE ALIBI centers around Hammond Cross, Special Assistant County Solicitor. (for those of you who don’t live in South Carolina and haven’t read THE WITNESS, you might not know that in that state, lawyers are called solicitors. In Texas we call them by other names.)\r\n\r\nHammond Cross hails from a wealthy Charleston family, but he eschews his heritage and the advantages it affords, even going far as to choose public service over a more lucrative career in criminal defense. He’s ambitious, and has his sights set on higher offices, but his goals aren’t strictly politically motivated. He’s also an aggressive prosecutor out to win for all the right reasons. He believes in what he’s doing and devotes himself to bringing criminals to justice.\r\n\r\nUntil . . .\r\n\r\nHe unwittingly becomes the alibi of an accused murderer.\r\n\r\nThe captivating and elusive woman with whom he had spent an overnight getaway — a meeting he mistook as happenstance — becomes the prime suspect in the most important criminal case Hammond’s career. If he prosecutes it successfully, he’ll inherit the top position from the retiring County Solicitor. If he doesn’t, he’ll have many people to answer to . . . not the least of which is himself.\r\n\r\nTo admit his own culpability is self-destructive. To fail is unthinkable. To win is to sacrifice the woman he’s come to love.\r\n([source][1])\r\n\r\n\r\n  [1]: https://sandrabrown.net/books/the-alibi/",
  "authors": [
    "Sandra Brown"
  ],
  "first_publish_year": 1999,
  "subjects": [
    "murder trials",
    "Legal stories",
    "Man-woman relationships",
    "Trials (Murder)",
    "Open Library Staff Picks",
    "American Psychological fiction",
    "Fiction",
    "Murder",
    "Suspense fiction",
    "Public prosecutors",
    "American Legal stories",
    "Psychological fiction",
    "Lawyers, fiction",
    "Charleston (s.c.), fiction",
    "Fiction, suspense",
    "Fiction, legal",
    "Large type books",
    "nyt:mass-market-paperback=2015-11-22",
    "New York Times bestseller",
    "Fiction, thrillers, suspense",
    "Procureurs généraux",
    "Romans, nouvelles",
    "Procès (Meurtre)"
  ],
  "language": [
    "eng",
    "ger",
    "rus",
    "pol",
    "fre",
    "chi"
  ],
  "openlibrary_url": "https://openlibrary.org/works/OL167331W"
}