{
  "id": "OL16805415W",
  "title": "Americanah",
  "description": "Americanah is a 2013 novel by the Nigerian author Chimamanda Ngozi Adichie, for which Adichie won the 2013 U.S. National Book Critics Circle Award for fiction. Americanah tells the story of a young Nigerian woman, Ifemelu, who immigrates to the United States to attend university. The novel traces Ifemelu's life in both countries, threaded by her love story with high school classmate Obinze.",
  "authors": [
    "Chimamanda Ngozi Adichie"
  ],
  "first_publish_year": 1969,
  "subjects": [
    "Nigerians",
    "Immigrants",
    "Refugees",
    "African-Americans",
    "literary fiction",
    "African-American fiction",
    "cultural heritage",
    "Fiction",
    "blogging",
    "romance",
    "corruption",
    "award:national_book_critics_circle_award=fiction",
    "National Book Critics Circle Award Winner",
    "Reading Level-Grade 7",
    "Reading Level-Grade 9",
    "Reading Level-Grade 8",
    "Reading Level-Grade 11",
    "Reading Level-Grade 10",
    "Reading Level-Grade 12",
    "1000blackgirlbooks",
    "Fiction, historical",
    "Nigeria, fiction",
    "Large type books",
    "FICTION / Literary",
    "FICTION / African American / General",
    "FICTION / Cultural Heritage",
    "nyt:trade-fiction-paperback=2014-03-23",
    "New York Times bestseller",
    "New York Times reviewed",
    "Fiction, historical, general",
    "Literary",
    "African American",
    "General",
    "English literature",
    "Inmigrantes",
    "Ficción",
    "Regugiados",
    "Nigeriano",
    "Ficcion",
    "History",
    "Romans, nouvelles",
    "Racisme",
    "Relations raciales",
    "Réfugiés",
    "Nigérians",
    "Livres en gros caractères",
    "Large print books",
    "Immigrants--fiction",
    "Refugees--fiction",
    "Nigerians--united states--fiction",
    "Nigerians--england--fiction",
    "Fiction--literary",
    "Fiction--african american--general",
    "Pr9387.9.a34354 a44 2013",
    "823/.92",
    "Fic019000 fic049000 fic051000",
    "Emigration and immigration"
  ],
  "language": [
    "eng",
    "hrv",
    "spa",
    "rus",
    "dut",
    "tur",
    "jpn",
    "fre"
  ],
  "openlibrary_url": "https://openlibrary.org/works/OL16805415W"
}