{
  "id": "OL1938270W",
  "title": "The spiffiest giant in town",
  "description": "George the giant, known for wearing his old patched clothes, finally buys new ones, but then gives them away to some needy animals.",
  "authors": [
    "Julia Donaldson"
  ],
  "first_publish_year": 2001,
  "subjects": [
    "Fiction",
    "Giants",
    "Clothing and dress",
    "Kindness",
    "Animals",
    "Juvenile fiction",
    "Pictorial works",
    "Children's fiction",
    "Giants, fiction",
    "Picture books",
    "Stories in rhyme",
    "Bilderbuch",
    "Dank",
    "Freigebigkeit",
    "Hilfsbereitschaft",
    "Kleidung",
    "Riese",
    "Tiere",
    "Humorous stories",
    "Animals, fiction",
    "Friendship, fiction",
    "Clothing and dress, fiction"
  ],
  "language": [
    "ita",
    "fre",
    "eng",
    "chi",
    "gle",
    "cat",
    "ger"
  ],
  "openlibrary_url": "https://openlibrary.org/works/OL1938270W"
}