{
  "id": "OL23197W",
  "title": "The Red Pony",
  "description": "Tells story of a young boy and his life on his father's ranch. Ownership of a red pony teaches ten-year-old Jody about life and death.",
  "authors": [
    "John Steinbeck"
  ],
  "first_publish_year": 1933,
  "subjects": [
    "Horses",
    "Horse",
    "Open Library Staff Picks",
    "Ponies",
    "Fiction",
    "Boys",
    "Ranch life",
    "Coming of age",
    "Loss (Psychology)",
    "Western stories",
    "American fiction (fictional works by one author)",
    "West (u.s.), fiction",
    "Children's fiction",
    "Horses, fiction",
    "Ponies, fiction",
    "Large type books",
    "Death",
    "Fuction",
    "Historical Fiction",
    "English Young adult literature",
    "American literature",
    "Juvenile fiction",
    "Garçons",
    "Romans, nouvelles",
    "Vie au ranch"
  ],
  "language": [
    "ger",
    "heb",
    "fre",
    "per",
    "chi",
    "dan",
    "dut",
    "tam",
    "und",
    "ice",
    "eng",
    "cat"
  ],
  "openlibrary_url": "https://openlibrary.org/works/OL23197W"
}