{
  "id": "OL2577482W",
  "title": "Ostatnie Życzenie",
  "description": "Pozycja, która przedstawia początki historii słynnego Geralta z Rivii. Sięgnij po tę lekturę i zanurz się w świecie, pełnym niebezpiecznych stworzeń, nierzadko napadających na ludzkie osady.\r\n\r\n\"Ostatnie życzenie\" to jeden ze zbiorów opowiadań z cyklu wiedźmińskiego, który zdobył ogromną popularność nie tylko w Polsce, ale i na całym świecie, między innymi za sprawą gry komputerowej, a następnie dzięki serialowi, wyprodukowanemu przez platformę Netflix.\r\n\r\nGłówny bohater, Geralt z Rivii, jest wiedźminem, czyli osobą, która w zamian za wynagrodzenie, pozbywa się rozlicznych potworów. Działa według ściśle określonego systemu moralnego, dzieląc wszystko na to, co dobre i na to, co złe, nie uznając natomiast niczego pośrodku. Nie zabija, jeśli nie musi tego robić. Woli stawiać na uroki, które czasem też mogą rozwiązać problem. W trakcie swoich przygód poznaje piękną czarodziejkę, Yennefer, która wzbudza w nim fascynację. Jakie zlecenia czekają na niego w najbliższej przyszłości?",
  "authors": [
    "Andrzej Sapkowski",
    "Danusia Stok"
  ],
  "first_publish_year": 1993,
  "subjects": [
    "Fantasy",
    "Fiction",
    "Translations into English",
    "Polish fiction",
    "Fiction, fantasy, general",
    "Fiction, fantasy, short stories",
    "nyt:mass-market-paperback=2015-07-05",
    "New York Times bestseller",
    "Fiction, fantasy, collections & anthologies",
    "Sorcerers",
    "nyt:trade-fiction-paperback=2020-01-26"
  ],
  "language": [
    "ita",
    "pol",
    "fre",
    "ger",
    "spa",
    "eng"
  ],
  "openlibrary_url": "https://openlibrary.org/works/OL2577482W"
}