{
  "id": "OL2940317W",
  "title": "The True Story of the Three Little Pigs",
  "description": "Goodreads Review:\r\n**You thought you knew the story of the “The Three Little Pigs”… You thought wrong.**\r\n \r\nIn this **hysterical and clever fracture fairy tale picture book that twists point** of view and perspective, young readers will finally hear the other side of the story of “The Three Little Pigs.”\r\n \r\n“**In this humorous story, Alexander T. Wolf tells his own outlandish version** of what really happens during his encounter with the three pigs…. Smith's simplistic and wacky illustrations add to the effectiveness of this fractured fairy tale.” —Children’s Literature\r\n \r\n**“Older kids (and adults) will find very funny.”** —School Library Journal",
  "authors": [
    "Jon Scieszka"
  ],
  "first_publish_year": 1989,
  "subjects": [
    "The True Story of the 3 Little Pigs!",
    "By A. Wolf (As Told to Jon Scieszka)",
    "1991 Scholastic first printing",
    "By A. Wolf",
    "his story",
    "actual story",
    "he says",
    "Front page news",
    "Cerdos",
    "Lobos",
    "Juvenile fiction",
    "Fiction",
    "Novela juvenil",
    "Pigs",
    "Swine",
    "Wolves",
    "Neighbors",
    "Gluttony",
    "Sneezing",
    "Truthfulness and falsehood",
    "Prisoners",
    "Children's fiction",
    "Bears, fiction",
    "Ficción juvenil",
    "Pigs, fiction",
    "Wolves, fiction",
    "Pigs in fiction",
    "Fairy tales",
    "Wolves in fiction",
    "Parodies, imitations",
    "Adaptations",
    "Humorous stories",
    "Picture books",
    "Spanish language materials",
    "Materiales en español",
    "Literatura juvenil",
    "Friendship, fiction"
  ],
  "language": [
    "eng",
    "chi",
    "por",
    "fre",
    "spa",
    "jpn",
    "kor",
    "ice"
  ],
  "openlibrary_url": "https://openlibrary.org/works/OL2940317W"
}