{
  "id": "OL455336W",
  "title": "The Marble Faun",
  "description": "Hawthorne's novel of Americans abroad, the first novel to explore the influence of European cultural ideas on American morality. Although it is set in Rome, the fictive world of The Marble Faun depends not on Italy's social or historical significance, but rather on its aesthetic importance as a definer of 'civilization'. As in The Scarlet Letter, Hawthorne is concerned here with the nature of transgression and guilt. A murder, motivated by love, affects not only Donatello, the murderer, but his beloved Miriam and their friends Hilda and Kenyon. As he explores the reactions of each to the crime, Hawthorne dramatizes both the freedoms a new cultural model inspires and the self-censoring conformities it requires. His examination of the influence of European culture on American travellers lay the groundwork for such later works of American fiction as Mark Twain's The Innocents Abroad and Henry James' The Portrait of a Lady.",
  "authors": [
    "Nathaniel Hawthorne"
  ],
  "first_publish_year": 1840,
  "subjects": [
    "Fiction",
    "Murder",
    "Women art students",
    "Americans",
    "Artists",
    "Nobility",
    "Classic Literature",
    "Literature",
    "Rome (Italy)",
    "Psychological fiction",
    "Love stories",
    "American fiction (fictional works by one author)",
    "Artists, fiction",
    "Rome (italy), fiction",
    "Fiction, psychological",
    "Fiction, romance, general",
    "Crime, fiction",
    "Women artists, fiction",
    "Italy, fiction",
    "Large type books",
    "Guilt",
    "Conscience",
    "History",
    "Étudiantes en art",
    "Romans, nouvelles",
    "Artistes",
    "Meurtre",
    "Long Now Manual for Civilization",
    "Readers",
    "American literature",
    "History and criticism",
    "Powieść amerykańska",
    "Tłumaczenia polskie"
  ],
  "language": [
    "fre",
    "eng",
    "pol"
  ],
  "openlibrary_url": "https://openlibrary.org/works/OL455336W"
}