{
  "id": "OL455663W",
  "title": "The House of the Seven Gables",
  "description": "In a sleepy little New England village stands a dark, weather-beaten, many-gabled house. This brooding mansion is haunted by a centuries-old curse that casts the shadow of ancestral sin upon the last four members of the distinctive Pyncheon family. Mysterious deaths threaten the living. Musty documents nestle behind hidden panels carrying the secret of the family's salvation -- or its downfall.\r\n\r\nHawthorne called The House of the Seven Gables \"a romance,\" and freely bestowed upon it many fascinating gothic touches. A brilliant intertwining of the popular, the symbolic, and the historical, the novel is a powerful exploration of personal and national guilt, a work that Henry James declared \"the closest approach we are likely to have to the Great American Novel.\"",
  "authors": [
    "Nathaniel Hawthorne"
  ],
  "first_publish_year": 1851,
  "subjects": [
    "Fiction",
    "Haunted houses in fiction",
    "Haunted houses",
    "Juvenile fiction",
    "Cartoons and comics",
    "Ghosts in fiction",
    "Ghosts",
    "Families",
    "Family",
    "Readers",
    "Readers in fiction",
    "Classic Literature",
    "Cliffs notes on",
    "CliffsNotes",
    "open_syllabus_project",
    "Domestic fiction",
    "Children: Babies Toddlers",
    "Open Library Staff Picks",
    "Social life and customs",
    "American Historical fiction",
    "Dictionaries",
    "English language",
    "French",
    "Spanish",
    "Korean",
    "False imprisonment",
    "Paranormal fiction",
    "Historical fiction",
    "German",
    "American literature",
    "American fiction (fictional works by one author)",
    "Fiction, historical",
    "Fiction, occult & supernatural",
    "Salem (mass.), fiction",
    "Fiction, horror",
    "Fiction, family life",
    "Puritans",
    "American fiction",
    "Fiction, romance, general",
    "General",
    "Secrets",
    "History",
    "Fiction, historical, general",
    "Occult fiction",
    "Greed",
    "18.06 Anglo-American literature",
    "House of the seven gables (Hawthorne, Nathaniel)",
    "House of the seven gables",
    "Maisons hantées",
    "Romans, nouvelles",
    "Readers (Primary)",
    "Devotional literature",
    "Bible",
    "Long Now Manual for Civilization",
    "Hawthorne, nathaniel, 1804-1864"
  ],
  "language": [
    "ger",
    "eng",
    "spa",
    "fre",
    "hrv"
  ],
  "openlibrary_url": "https://openlibrary.org/works/OL455663W"
}