{
  "id": "OL4720160W",
  "title": "The Time Traveler's Wife",
  "description": "Audrey Niffenegger's innovative debut, The Time Traveler's Wife, is the story of Clare, a beautiful art student, and Henry, an adventuresome librarian, who have known each other since Clare was six and Henry was thirty-six, and were married when Clare was twenty-three and Henry thirty-one. Impossible but true, because Henry is one of the first people diagnosed with Chrono-Displacement Disorder: periodically his genetic clock resets and he finds himself misplaced in time, pulled to moments of emotional gravity in his life, past and future. His disappearances are spontaneous, his experiences unpredictable, alternately harrowing and amusing.\r\n([source][1])\r\n\r\n\r\n  [1]: https://www.audreyniffenegger.com/published-books/2015/4/22/the-time-travelers-wife-2005",
  "authors": [
    "Audrey Niffenegger"
  ],
  "first_publish_year": 2003,
  "subjects": [
    "mutants",
    "love",
    "death",
    "amputation",
    "sex",
    "time",
    "science fiction",
    "romance",
    "foreshadowing",
    "first-person narrative",
    "hypothermia",
    "frostbite",
    "miscarriage",
    "vasectomy",
    "stress",
    "Spanish language materials",
    "Spanish language",
    "Fiction",
    "domestic fiction",
    "Librarians",
    "Married people",
    "Viaje a través del tiempo",
    "Women art students",
    "Fantasy fiction",
    "Bibliotecarios",
    "Ficción",
    "Personas casadas",
    "Time travel",
    "Viajes a través del tiempo",
    "Fiction, fantasy, general",
    "Married people, fiction",
    "Fiction, romance, time travel",
    "Librarians, fiction",
    "Women artists, fiction",
    "FICTION / Literary",
    "FICTION / Historical",
    "Large type books",
    "Chang pian xiao shuo",
    "nyt:trade-fiction-paperback=2009-07-05",
    "New York Times bestseller",
    "Bibliothécaires",
    "Romans, nouvelles",
    "Voyages dans le temps",
    "Couples mariés",
    "Étudiantes en art",
    "Women artists",
    "Librarians--fiction",
    "Time travel--fiction",
    "Married people--fiction",
    "Women art students--fiction",
    "Fictional works",
    "Ps3564.i362 t56 2003b",
    "813/.54"
  ],
  "language": [
    "ita",
    "rus",
    "ger",
    "spa",
    "eng",
    "chi"
  ],
  "openlibrary_url": "https://openlibrary.org/works/OL4720160W"
}