{
  "id": "OL66544W",
  "title": "Persuasion",
  "description": "Persuasion tells the love story of Anne Elliot and Captain Frederick Wentworth, whose sister rents Miss Elliot's father's house, after the Napoleonic Wars come to an end. The story is set in 1814. The book itself is Jane Austen's last published book, published posthumously in December of 1818.",
  "authors": [
    "Jane Austen"
  ],
  "first_publish_year": 1789,
  "subjects": [
    "Fiction, Romance, Historical, Regency",
    "Love stories, English",
    "Moški in ženske",
    "V leposlovju",
    "Medosebni odnosi",
    "Družbene razmere",
    "Social life and customs",
    "Rejection (Psychology)",
    "Officers",
    "Great Britain. Royal Navy",
    "Great Britain",
    "Manners and customs",
    "Armed Forces, fiction",
    "British and irish fiction (fictional works by one author)",
    "Man-woman relationships, fiction",
    "England, fiction",
    "Great Britain, fiction",
    "Austen, jane, 1775-1817",
    "Fiction, psychological",
    "English literature",
    "Manuscripts",
    "English Manuscripts",
    "Facsimiles",
    "Gentry",
    "Mate selection, fiction",
    "Reading Level-Grade 9",
    "Reading Level-Grade 8",
    "Reading Level-Grade 11",
    "Reading Level-Grade 10",
    "Reading Level-Grade 12",
    "Literature and fiction (general)",
    "Fiction, sagas",
    "Literature",
    "England -- Social life and customs -- 19th century -- Fiction",
    "Psychological fiction",
    "Young women, fiction",
    "Motherless families, fiction",
    "Rejection (Psychology), fiction",
    "First loves, fiction",
    "Dysfunctional families, fiction",
    "Ship captains,  fiction",
    "Jeunes femmes",
    "Romans, nouvelles",
    "Mœurs et coutumes",
    "Sisters",
    "Sœurs",
    "Relations entre hommes et femmes",
    "Stinehour press. 1977",
    "Social classes",
    "Courtship, fiction",
    "Fiction, romance, general",
    "Fiction, general",
    "Austen, jane , 1775-1817",
    "Elliot, anne , 1787-",
    "Rejection (psychology)--fiction",
    "First loves--fiction",
    "Young women--england--fiction",
    "Pr4034 .p4 2008",
    "823/.7",
    "Pr4034 .p4 1998b",
    "Fiction, historical, general",
    "Psychology",
    "Fiction",
    "Courtship",
    "Motherless families",
    "Dysfunctional families",
    "Ship captains",
    "First loves",
    "Young women",
    "Long Now Manual for Civilization",
    "General",
    "LITERARY CRITICISM",
    "Man-woman relationships"
  ],
  "language": [
    "eng",
    "ita",
    "cat",
    "ger",
    "rus",
    "tur",
    "pol",
    "chi",
    "fre",
    "vie",
    "spa",
    "por",
    "und"
  ],
  "openlibrary_url": "https://openlibrary.org/works/OL66544W"
}