{
  "id": "OL76837W",
  "title": "The Da Vinci Code",
  "description": "The Da Vinci Code is a 2003 mystery thriller novel by Dan Brown. It is Brown's second novel to include the character Robert Langdon: the first was his 2000 novel Angels & Demons. The Da Vinci Code follows \"symbologist\" Robert Langdon and cryptologist Sophie Neveu after a murder in the Louvre Museum in Paris causes them to become involved in a battle between the Priory of Sion and Opus Dei over the possibility of Jesus Christ and Mary Magdalene having had a child together.\r\n\r\n\r\n----------\r\nSee also:\r\n[The Da Vinci Code [1/2]](https://openlibrary.org/works/OL24164822W)\r\n[The Da Vinci Code [2/2]](https://openlibrary.org/works/OL24210437W)\r\n\r\n\t\t\r\nContained in:\r\n[Angels & Demons / The Da Vinci Code](https://openlibrary.org/works/OL15290520W)",
  "authors": [
    "Dan Brown"
  ],
  "first_publish_year": 2003,
  "subjects": [
    "Suspense & Thriller",
    "Spiritual Fiction",
    "hieros gamos",
    "Priory of Sion",
    "Holy Grail",
    "Vitruvian Man",
    "Fibonacci sequence",
    "safe deposit boxes",
    "mystery & suspense",
    "Templars",
    "Manuscripts",
    "Last Supper in art",
    "Symbolism in architecture",
    "suspense fiction",
    "adventure fiction",
    "Catholics",
    "puzzles",
    "International thriller",
    "Code and cipher stories",
    "Mystery fiction",
    "crimes against art museum curators",
    "art appreciation",
    "thrillers",
    "suspense",
    "Historical Mystery & Detective Fiction",
    "Religious fiction",
    "Mystery",
    "Aventures",
    "Religious articles",
    "Crimes against",
    "Romans",
    "Appreciation",
    "Occultisme",
    "Art museum curators",
    "Sociedades secretas",
    "Grial",
    "Ficción",
    "Robert Langdon (Fictitious character)",
    "Novela",
    "Powiesc amerykanska",
    "T¿umaczenia polskie",
    "Polish language materials",
    "Secret societies",
    "Cryptographers",
    "Fiction",
    "Grail",
    "Reading Level-Grade 9",
    "Reading Level-Grade 8",
    "Reading Level-Grade 11",
    "Reading Level-Grade 10",
    "Reading Level-Grade 12",
    "Detective and mystery stories",
    "Cryptography",
    "Fictional Works",
    "American fiction",
    "Leonardo, da vinci, 1452-1519, fiction",
    "Paris (france), fiction",
    "Fiction, mystery & detective, general",
    "Langdon, robert (fictitious character), fiction",
    "Fiction, thrillers",
    "Fiction, thrillers, general",
    "Large type books",
    "Fiction, suspense",
    "Museumsdirektor",
    "Bruderschaft",
    "Mord",
    "Manuscritos",
    "Criptografía",
    "Belletristische Darstellung",
    "Maria Magdalena",
    "New York Times reviewed",
    "Religious",
    "General",
    "England, fiction",
    "Fiction, thrillers, suspense",
    "Chang pian xiao shuo",
    "collectionid:dbrl"
  ],
  "language": [
    "ita",
    "kor",
    "lit",
    "mal",
    "ind",
    "spa",
    "jpn",
    "vie",
    "per",
    "heb",
    "por",
    "swe",
    "cat",
    "tur",
    "pol",
    "eng",
    "rus",
    "ara",
    "dut",
    "fre",
    "gre",
    "ger",
    "chi"
  ],
  "openlibrary_url": "https://openlibrary.org/works/OL76837W"
}