{
  "id": "OL8972751W",
  "title": "Nesnesitelná lehkost bytí",
  "description": "Interweaves story and dream, past and present, and philosophy and poetry in a sardonic and erotic tale of two couples--Tomas and Teresa, and Sabina and her Swiss lover, Gerhart.",
  "authors": [
    "Milan Kundera"
  ],
  "first_publish_year": 1984,
  "subjects": [
    "German fiction",
    "Fiction, general",
    "Fiction",
    "Love",
    "Man-woman relationships",
    "Love stories",
    "Identity (Psychology)",
    "Surgeons",
    "History",
    "Translations from Czech",
    "Translations into English",
    "Czech fiction",
    "English fiction",
    "Continental european fiction (fictional works by one author)",
    "Novela",
    "Relaciones hombre-mujer",
    "Cirujanos",
    "Ficción",
    "Liebesbeziehung",
    "Arzt",
    "Belletristische Darstellung",
    "Large type books",
    "Chang pian xiao shuo",
    "Relaciones Hombre - Mujer",
    "Amor en la literatura",
    "open_syllabus_project",
    "Prague (czech republic), fiction",
    "Romance fiction",
    "Relations entre hommes et femmes",
    "Romans, nouvelles",
    "Cuentos de amor",
    "Literary collections",
    "Fictional Works [Publication Type]",
    "Milan Kundera",
    "Underground literature"
  ],
  "language": [
    "tur",
    "pol",
    "fre",
    "ara",
    "ger",
    "cze",
    "cmn",
    "vie",
    "eng",
    "ita",
    "chi",
    "spa",
    "rus",
    "rum"
  ],
  "openlibrary_url": "https://openlibrary.org/works/OL8972751W"
}